CMakeLists.txt
LICENSE.txt
MANIFEST.in
README.md
setup.py
cytoplay.egg-info/PKG-INFO
cytoplay.egg-info/SOURCES.txt
cytoplay.egg-info/dependency_links.txt
cytoplay.egg-info/not-zip-safe
cytoplay.egg-info/top_level.txt
pycytoplay/CMakeLists.txt
pycytoplay/package/__init__.py
pycytoplay/package/play2D
pycytoplay/package/play3D
pycytoplay/package/sim2D
pycytoplay/package/sim3D
pycytoplay/package/sim_wrapper.py
pycytosim/CMakeLists.txt
src/CMakeLists.txt
src/base/CMakeLists.txt
src/base/assert_macro.h
src/base/backtrace.cc
src/base/backtrace.h
src/base/bitmap.cc
src/base/buddy.h
src/base/byteswap.h
src/base/exceptions.cc
src/base/exceptions.h
src/base/filepath.cc
src/base/filepath.h
src/base/filewrapper.cc
src/base/filewrapper.h
src/base/flexset.h
src/base/glossary.cc
src/base/glossary.h
src/base/inventoried.h
src/base/inventory.cc
src/base/inventory.h
src/base/iowrapper.cc
src/base/iowrapper.h
src/base/messages.cc
src/base/messages.h
src/base/operator_new.cc
src/base/print_color.cc
src/base/print_color.h
src/base/property.cc
src/base/property.h
src/base/property_list.cc
src/base/property_list.h
src/base/rdtsc.h
src/base/signal_handlers.cc
src/base/signal_handlers.h
src/base/stream_func.cc
src/base/stream_func.h
src/base/time_date.cc
src/base/time_date.h
src/base/timer.h
src/base/tokenizer.cc
src/base/tokenizer.h
src/cpython/couple_modules.h
src/cpython/fiber_modules.h
src/cpython/glossary_modules.h
src/cpython/hand_modules.h
src/cpython/interface_modules.h
src/cpython/lattice_modules.h
src/cpython/meca_modules.h
src/cpython/object_modules.h
src/cpython/organizer_modules.h
src/cpython/point_modules.h
src/cpython/pycytoplay.cc
src/cpython/pycytosim.cc
src/cpython/pycytosim.h
src/cpython/python_frame.h
src/cpython/python_utilities.h
src/cpython/simul_modules.h
src/cpython/single_modules.h
src/cpython/solid_modules.h
src/cpython/space_modules.h
src/cpython/thread_modules.h
src/disp/CMakeLists.txt
src/disp/display.cc
src/disp/display.h
src/disp/display1.cc
src/disp/display1.h
src/disp/display2.cc
src/disp/display2.h
src/disp/display3.cc
src/disp/display3.h
src/disp/display_color.cc
src/disp/display_prop.cc
src/disp/display_prop.h
